compose_sdk/__init__.py
compose_sdk/api/__init__.py
compose_sdk/api/constants.py
compose_sdk/api/handler.py
compose_sdk/api/ws_message.py
compose_sdk/app/__init__.py
compose_sdk/app/appDefinition.py
compose_sdk/app/appRunner.py
compose_sdk/app/page.py
compose_sdk/app/route.py
compose_sdk/app/state.py
compose_sdk/composeHandler.py
compose_sdk/core/__init__.py
compose_sdk/core/audit_log.py
compose_sdk/core/component_update_cache.py
compose_sdk/core/compress.py
compose_sdk/core/date_utils.py
compose_sdk/core/debug.py
compose_sdk/core/eventType.py
compose_sdk/core/file.py
compose_sdk/core/generator/__init__.py
compose_sdk/core/generator/base.py
compose_sdk/core/generator/buttonInteraction.py
compose_sdk/core/generator/displayInteraction.py
compose_sdk/core/generator/dynamicInteraction.py
compose_sdk/core/generator/inputInteraction/__init__.py
compose_sdk/core/generator/inputInteraction/tableComponent.py
compose_sdk/core/generator/layoutInteraction.py
compose_sdk/core/generator/pageInteraction.py
compose_sdk/core/json.py
compose_sdk/core/rate_limiter.py
compose_sdk/core/run_hook_function.py
compose_sdk/core/smart_debounce.py
compose_sdk/core/static_tree/__init__.py
compose_sdk/core/static_tree/configure_submit_button.py
compose_sdk/core/static_tree/configure_table_pagination.py
compose_sdk/core/static_tree/diff/__init__.py
compose_sdk/core/static_tree/diff/apply_ids.py
compose_sdk/core/static_tree/diff/diff.py
compose_sdk/core/static_tree/diff/metadata.py
compose_sdk/core/static_tree/find_component.py
compose_sdk/core/static_tree/resolve_coroutines.py
compose_sdk/core/static_tree/static_tree.py
compose_sdk/core/static_tree/validate.py
compose_sdk/core/string.py
compose_sdk/core/table_state.py
compose_sdk/core/types.py
compose_sdk/core/ui/__init__.py
compose_sdk/core/ui/componentGenerators.py
compose_sdk/core/ui/constants.py
compose_sdk/core/ui/interactive_component_type.py
compose_sdk/core/ui/types/__init__.py
compose_sdk/core/ui/types/annotation.py
compose_sdk-0.27.8.dist-info/METADATA
compose_sdk-0.27.8.dist-info/WHEEL
compose_sdk-0.27.8.dist-info/RECORD
