Metadata-Version: 2.1
Name: compose-sdk
Version: 0.27.8
Summary: The open-source SDK for building custom internal tools.
Home-page: https://github.com/compose-dev/compose/tree/main/packages/sdk/python
License: AGPL-3.0-or-later
Keywords: internal tool,internal app,ui builder,tool,app,ui
Author: Atul Jalan
Author-email: atul@composehq.com
Maintainer: Atul Jalan
Maintainer-email: atul@composehq.com
Requires-Python: >=3.9
Classifier: License :: OSI Approved :: GNU Affero General Public License v3 or later (AGPLv3+)
Classifier: Programming Language :: Python :: 3
Classifier: Programming Language :: Python :: 3.9
Classifier: Programming Language :: Python :: 3.10
Classifier: Programming Language :: Python :: 3.11
Classifier: Programming Language :: Python :: 3.12
Requires-Dist: orjson (>=3.10.15,<4.0.0)
Requires-Dist: pandas (>=2.0,<3.0)
Requires-Dist: typing-extensions (>=4.12.2,<5.0.0)
Requires-Dist: websockets (>=15.0,<16.0)
Project-URL: Repository, https://github.com/compose-dev/compose
